README.md
setup.py
pierskarsenbarg_pulumi_ngrok/__init__.py
pierskarsenbarg_pulumi_ngrok/_inputs.py
pierskarsenbarg_pulumi_ngrok/_utilities.py
pierskarsenbarg_pulumi_ngrok/agent_ingress.py
pierskarsenbarg_pulumi_ngrok/api_key.py
pierskarsenbarg_pulumi_ngrok/certificate_authority.py
pierskarsenbarg_pulumi_ngrok/credential.py
pierskarsenbarg_pulumi_ngrok/endpoint_configuration.py
pierskarsenbarg_pulumi_ngrok/event_destination.py
pierskarsenbarg_pulumi_ngrok/event_subscription.py
pierskarsenbarg_pulumi_ngrok/ip_policy.py
pierskarsenbarg_pulumi_ngrok/ip_policy_rule.py
pierskarsenbarg_pulumi_ngrok/ip_restriction.py
pierskarsenbarg_pulumi_ngrok/outputs.py
pierskarsenbarg_pulumi_ngrok/provider.py
pierskarsenbarg_pulumi_ngrok/pulumi-plugin.json
pierskarsenbarg_pulumi_ngrok/py.typed
pierskarsenbarg_pulumi_ngrok/reserved_address.py
pierskarsenbarg_pulumi_ngrok/reserved_domain.py
pierskarsenbarg_pulumi_ngrok/ssh_certificate_authority.py
pierskarsenbarg_pulumi_ngrok/ssh_credential.py
pierskarsenbarg_pulumi_ngrok/ssh_host_certificate.py
pierskarsenbarg_pulumi_ngrok/ssh_user_certificate.py
pierskarsenbarg_pulumi_ngrok/tls_certificate.py
pierskarsenbarg_pulumi_ngrok.egg-info/PKG-INFO
pierskarsenbarg_pulumi_ngrok.egg-info/SOURCES.txt
pierskarsenbarg_pulumi_ngrok.egg-info/dependency_links.txt
pierskarsenbarg_pulumi_ngrok.egg-info/not-zip-safe
pierskarsenbarg_pulumi_ngrok.egg-info/requires.txt
pierskarsenbarg_pulumi_ngrok.egg-info/top_level.txt
pierskarsenbarg_pulumi_ngrok/config/__init__.py
pierskarsenbarg_pulumi_ngrok/config/vars.py